odoo/addons/l10n_br_base_l10n_br_compat/README.rst
odoo/addons/l10n_br_base_l10n_br_compat/__init__.py
odoo/addons/l10n_br_base_l10n_br_compat/__manifest__.py
odoo/addons/l10n_br_base_l10n_br_compat/hooks.py
odoo/addons/l10n_br_base_l10n_br_compat/i18n/l10n_br_base_l10n_br_compat.pot
odoo/addons/l10n_br_base_l10n_br_compat/readme/CONTRIBUTORS.md
odoo/addons/l10n_br_base_l10n_br_compat/readme/DESCRIPTION.md
odoo/addons/l10n_br_base_l10n_br_compat/static/description/icon.png
odoo/addons/l10n_br_base_l10n_br_compat/static/description/index.html
odoo/addons/l10n_br_base_l10n_br_compat/views/res_company_view.xml
odoo/addons/l10n_br_base_l10n_br_compat/views/res_partner_views.xml
odoo_addon_l10n_br_base_l10n_br_compat-18.0.2.0.0.dist-info/METADATA
odoo_addon_l10n_br_base_l10n_br_compat-18.0.2.0.0.dist-info/WHEEL
odoo_addon_l10n_br_base_l10n_br_compat-18.0.2.0.0.dist-info/top_level.txt
odoo_addon_l10n_br_base_l10n_br_compat-18.0.2.0.0.dist-info/RECORD
