Metadata-Version: 2.1
Name: odoo-addon-l10n_br_base_l10n_br_compat
Version: 18.0.2.0.0
Requires-Python: >=3.10
Requires-Dist: odoo-addon-l10n_br_base==18.0.*
Requires-Dist: odoo==18.0.*
Summary: Compatibility with the l10n_br module
Home-page: https://github.com/OCA/l10n-brazil
License: AGPL-3
Author: Akretion, Odoo Community Association (OCA)
Author-email: support@odoo-community.org
Classifier: Programming Language :: Python
Classifier: Framework :: Odoo
Classifier: Framework :: Odoo :: 18.0
Classifier: License :: OSI Approved :: GNU Affero General Public License v3
